ir_eval_numba/__init__.py
ir_eval_numba/metrics.py
ir_eval_numba/py.typed
ir_eval_numba-1.1.0.dist-info/METADATA
ir_eval_numba-1.1.0.dist-info/WHEEL
ir_eval_numba-1.1.0.dist-info/licenses/LICENSE
ir_eval_numba-1.1.0.dist-info/RECORD
